{
  "version": "0.2",
  "useGitignore": true,
  "language": "en-GB",
  "dictionaries": ["en-gb"],
  "words": [
    "CABANA",
    "cabanacollections",
    "optimise",
    "optimised",
    "optimiser",
    "optimisers",
    "optimisation",
    "optimisations",
    "initialise",
    "organisation",
    "organisations",
    "reimagined",
    "microplastic",
    "microplastics",
    "wellbeing",
    "Lyocell",
    "TENCEL",
    "OAIC",
    "ACAT",
    "Afterpay",
    "Amex",
    "elastane",
    "Elastane",
    "Flatlock",
    "coverstitch",
    "wordmark",
    "underbust",
    "zoomable",
    "FOMO",
    "AEST",
    "Chopard",
    "bralettes",
    "ecommerce",
    "recordkeeping",
    "Movember",
    "mateship",
    "Toora",
    "wicking",
    "inseam",
    "tagless",
    "odors",
    "Mens",
    "mens",
    "womens",
    "Bralette",
    "bralette",
    "gaoptout",
    "dlpage",
    "OAIC",
    "signup",
    "heatmaps",
    "Contentful",
    "Menslink",
    "EveryMan",
    "YWCA",
    "UNWomen",
    "BeyondBlue",
    "playsinline",
    "nums"
  ],
  "ignorePaths": [
    "node_modules/**",
    "package-lock.json",
    "**/dist/**",
    "**/build/**",
    "CABANA_Cleanup_Report.md",
    "cspell.json"
  ]
}
